{
  "dataList": [
    {
      "id": 0,
      "place": "คาสิโนชั้น 2",
      "model": "파우스트",
      "content": "บรรยากาศในชั้นนี้เปลี่ยนไปอย่างได้ชัด เหมือนกับว่ามีซินดิเคทอีกกลุ่มหนึ่งได้ยึดชั้นนี้ไว้เเล้ว"
    },
    {
      "id": 1,
      "model": "흥겨운마리아치조직원",
      "teller": "นักดนตรีผู้ร่าเริง",
      "title": "Los Mariachis",
      "content": "เฮ้ ทุกคน! ทำไมสีหน้าดูสิ้นหวังหม่นหมองกันไปหมดเลยเนี่ยหึม?"
    },
    {
      "id": 2,
      "model": "흥겨운마리아치조직원",
      "teller": "นักดนตรีผู้ร่าเริง",
      "title": "Los Mariachis",
      "content": " ไม่รู้กฎที่นี้หรือไง? หน้าตาบูดบึ้งเเบบนั้นไม่เอานะ ใส่หมวกเเล้วมาเต้นกันดีกว่า!"
    },
    {
      "id": 3,
      "model": "료슈",
      "content": "มองหน้าฉันเเล้วพูดเเบบนั้นเนี่ยนะ? กู จะ หคหม."
    },
    {
      "id": 4,
      "model": "흥겨운마리아치조직원",
      "teller": "นักดนตรีผู้ร่าเริง",
      "title": "Los Mariachis",
      "content": "ห-หมายความว่าไง?!"
    },
    {
      "id": 5,
      "model": "료슈",
      "content": "หักคอให้หมด ไง"
    },
    {
      "id": 6,
      "model": "단테",
      "content": "<ใจเย็นนะ เรียวชู… อย่าไปหาเรื่องสู้ง่ายๆเเบบนั้นสิ—>"
    },
    {
      "id": 7,
      "model": "흥겨운마리아치조직원",
      "teller": "นักดนตรีผู้ร่าเริง",
      "title": "Los Mariachis",
      "content": "เห ช่างมันล่ะกัน ไอหมอนี่ดูหน้าตามีปัญหากว่าเธออีกเนาะ? งั้นเข็มไหนเป็นตาของนายล่ะ?"
    },
    {
      "id": 8,
      "model": "단테",
      "content": "<…เรียวชู พร้อมซัดยัง?>"
    },
    {
      "id": 9,
      "model": "료슈",
      "content": "พร้อมนานเเล้ว ดันเต้"
    }
  ]
}